AUTHORS
ChangeLog
HISTORY.rst
README.rst
requirements.txt
setup.cfg
setup.py
test-requirements.txt
tox.ini
bin/roboticeclient
docs/Makefile
docs/make.bat
docs/source/conf.py
docs/source/contributors.rst
docs/source/index.rst
docs/source/tasks.rst
docs/source/control/overview.rst
python_roboticeclient.egg-info/PKG-INFO
python_roboticeclient.egg-info/SOURCES.txt
python_roboticeclient.egg-info/dependency_links.txt
python_roboticeclient.egg-info/not-zip-safe
python_roboticeclient.egg-info/pbr.json
python_roboticeclient.egg-info/requires.txt
python_roboticeclient.egg-info/top_level.txt
roboticeclient/__init__.py
roboticeclient/client.py
roboticeclient/exceptions.py
roboticeclient/common/__init__.py
roboticeclient/common/_i18n.py
roboticeclient/common/client.py
roboticeclient/common/django.py
roboticeclient/common/horizon.py
roboticeclient/common/importutils.py
roboticeclient/common/manager.py
roboticeclient/control/__init__.py
roboticeclient/control/client.py
roboticeclient/control/shell.py
roboticeclient/control/v1/__init__.py
roboticeclient/control/v1/base.py
roboticeclient/control/v1/managers/__init__.py
roboticeclient/control/v1/managers/actions.py
roboticeclient/control/v1/managers/auth.py
roboticeclient/control/v1/managers/base.py
roboticeclient/control/v1/managers/const.py
roboticeclient/control/v1/managers/device_catalog.py
roboticeclient/control/v1/managers/devices.py
roboticeclient/control/v1/managers/hosts.py
roboticeclient/control/v1/managers/identity.py
roboticeclient/control/v1/managers/locations.py
roboticeclient/control/v1/managers/plans.py
roboticeclient/control/v1/managers/systems.py
roboticeclient/control/v1/managers/tasks.py
roboticeclient/control/v1/managers/users.py
roboticeclient/control/v1/managers/workers.py
roboticeclient/robotice/__init__.py
roboticeclient/robotice/client.py
roboticeclient/robotice/shell.py
roboticeclient/robotice/v1/__init__.py
roboticeclient/robotice/v1/base.py
roboticeclient/robotice/v1/managers/__init__.py
roboticeclient/robotice/v1/managers/actions.py
roboticeclient/robotice/v1/managers/base.py
roboticeclient/robotice/v1/managers/devices.py
roboticeclient/robotice/v1/managers/plans.py
roboticeclient/robotice/v1/managers/systems.py
roboticeclient/robotice/v1/managers/tasks.py
roboticeclient/robotice/v1/managers/workers.py
